elasticmock/__init__.py
elasticmock/fake_cluster.py
elasticmock/fake_elasticsearch.py
elasticmock/fake_indices.py
elasticmock/behaviour/__init__.py
elasticmock/behaviour/server_failure.py
elasticmock/utilities/__init__.py
elasticmock/utilities/decorator.py
tests/__init__.py
tests/tox_banner.py
tests/fake_cluster/__init__.py
tests/fake_cluster/test_health.py
tests/fake_elasticsearch/__init__.py
tests/fake_elasticsearch/test_bulk.py
tests/fake_elasticsearch/test_count.py
tests/fake_elasticsearch/test_delete.py
tests/fake_elasticsearch/test_exists.py
tests/fake_elasticsearch/test_get.py
tests/fake_elasticsearch/test_index.py
tests/fake_elasticsearch/test_info.py
tests/fake_elasticsearch/test_instance.py
tests/fake_elasticsearch/test_ping.py
tests/fake_elasticsearch/test_scroll.py
tests/fake_elasticsearch/test_search.py
tests/fake_elasticsearch/test_suggest.py
tests/fake_elasticsearch/behaviour/__init__.py
tests/fake_elasticsearch/behaviour/test_server_failure.py
tests/fake_indices/__init__.py
tests/fake_indices/test_create.py
tests/fake_indices/test_delete.py
tests/fake_indices/test_exists.py
tests/fake_indices/test_refresh.py
ElasticMockNew-1.8.1.dist-info/LICENSE
ElasticMockNew-1.8.1.dist-info/METADATA
ElasticMockNew-1.8.1.dist-info/WHEEL
ElasticMockNew-1.8.1.dist-info/top_level.txt
ElasticMockNew-1.8.1.dist-info/RECORD
