Metadata-Version: 2.1
Name: ElasticMockNew
Version: 1.8.1
Summary: Python Elasticsearch Mock for test purposes with new features
Home-page: https://github.com/t-bittarn/elasticmock
Author: t bittarn
Author-email: t@bittarn.com
License: UNKNOWN
Platform: UNKNOWN
Classifier: Environment :: Web Environment
Classifier: Intended Audience :: Developers
Classifier: Operating System :: OS Independent
Classifier: Programming Language :: Python
Classifier: Programming Language :: Python :: 3
Classifier: Programming Language :: Python :: 3.6
Classifier: Programming Language :: Python :: 3.7
Classifier: Programming Language :: Python :: 3.8
Classifier: License :: OSI Approved :: MIT License
Classifier: Topic :: Software Development :: Libraries :: Python Modules
License-File: LICENSE
Requires-Dist: elasticsearch
Requires-Dist: mock
Requires-Dist: python-dateutil
